adder.v
`define AND and #50
`define OR or #50
`define XOR xor #50
`define NOT not #50

// Adder circuit

module structFullAdder
(
    output sum,
    output carryout,
    input a,
    input b,
    input carryin
);
  wire AxorB;
	wire AandB;
	wire AxorBandCarryIn;

	`XOR (AxorB, a, b);
	`XOR (sum, AxorB, carryin);
	`AND (AandB, a, b);
	`AND (AxorBandCarryIn, AxorB, carryin);
	`OR (carryout, AxorBandCarryIn, AandB);
endmodule

module FullAdder4bit
(
  output[3:0] sum,  // 2's complement sum of a and b
  output carryout, carryout2,  // Carry out of the summation of a and b
  output overflow,  // True if the calculation resulted in an overflow
  input[3:0] a,     // First operand in 2's complement format
  input[3:0] b      // Second operand in 2's complement format
);

	wire carryout0; //Carryout of first adder.
	wire carryout1; //Carryout of second adder.

	structFullAdder a0(sum[0], carryout0, a[0], b[0], 1'b0); //Structural Full Adder with specific initial values.
	structFullAdder a1(sum[1], carryout1, a[1], b[1], carryout0);
	structFullAdder a2(sum[2], carryout2, a[2], b[2], carryout1);
	structFullAdder a3(sum[3], carryout, a[3], b[3], carryout2);

  `XOR (overflow, carryout2, carryout); //XOR handles overflow.
endmodule

adder.t.v
`timescale 1 ns / 1 ps
`include "adder.v"

module test4BitFullAdder();
  reg[3:0] a;
	reg[3:0] b;
	wire[3:0] sum;
  wire carryout;
  wire carryout2;
	wire overflow;
  //integer i;
  //integer j;

	FullAdder4bit adder(sum, carryout, carryout2, overflow, a, b);

  initial begin
  	$dumpfile("fulladder.vcd");
  	$dumpvars(0, a[3:0], b[3:0], sum[3:0], carryout, carryout2, overflow);

    $display(" a  |  b  |  S  C2 |  COut  |  OverFlow");
    //for(i = -8; i < 8; i = i + 7)
    //begin
      //for(j = -8; j < 8; j = j + 1)
      //begin

    a = -8;
    b = -8;
    #1000
    $display(" %d |  %d | %d   %b |    %b   |        %b ", $signed(a), $signed(b), $signed(sum), carryout2, carryout, overflow);
    a = 7;
    b = -8;
    #1000
    $display(" %d |  %d | %d   %b |    %b   |        %b ", $signed(a), $signed(b), $signed(sum), carryout2, carryout, overflow);
    a = 7;
    b = 7;
    #1000
    $display(" %d |  %d | %d   %b |    %b   |        %b ", $signed(a), $signed(b), $signed(sum), carryout2, carryout, overflow);
    a = 5;
    b = 2;
    #1000
    $display(" %d |  %d | %d   %b |    %b   |        %b ", $signed(a), $signed(b), $signed(sum), carryout2, carryout, overflow);
    a = 5;
    b = 3;
    #1000
    $display(" %d |  %d | %d   %b |    %b   |        %b ", $signed(a), $signed(b), $signed(sum), carryout2, carryout, overflow);
    a = -5;
    b = -3;
    #1000
    $display(" %d |  %d | %d   %b |    %b   |        %b ", $signed(a), $signed(b), $signed(sum), carryout2, carryout, overflow);
    a = -5;
    b = -4;
    #1000
    $display(" %d |  %d | %d   %b |    %b   |        %b ", $signed(a), $signed(b), $signed(sum), carryout2, carryout, overflow);

      //end
    //end

    end
endmodule

fulladder.vcd
$date
	Thu Sep 28 00:20:04 2017
$end
$version
	Icarus Verilog
$end
$timescale
	1ps
$end
$scope module test4BitFullAdder $end
$var reg 4 ! a [3:0] $end
$upscope $end
$scope module test4BitFullAdder $end
$var reg 4 " b [3:0] $end
$upscope $end
$scope module test4BitFullAdder $end
$var wire 4 # sum [3:0] $end
$upscope $end
$scope module test4BitFullAdder $end
$var wire 1 $ carryout $end
$upscope $end
$scope module test4BitFullAdder $end
$var wire 1 % carryout2 $end
$upscope $end
$scope module test4BitFullAdder $end
$var wire 1 & overflow $end
$upscope $end
$enddefinitions $end
#0
$dumpvars
x&
x%
x$
bx #
b0 "
b0 !
$end
#100000
bx0 #
#150000
0%
0$
bx00 #
#200000
b0 #
0&
#1000000
b1111 "
b1111 !
#1100000
1%
1$
#1150000
b1110 #
#2000000
b1 "
b1 !
#2100000
0%
0$
#2150000
b10 #
#3000000
b1001 "
b111 !
#3100000
b1100 #
#3200000
b1000 #
#3250000
1%
#3300000
b0 #
1&
#3350000
1$
#3400000
0&
#4000000
b1110 "
b110 !
#4100000
b110 #
#4150000
b100 #
#5000000
b101 "
#5100000
b1111 #
#5150000
b1011 #
0$
#5200000
1&
#6000000
b1001 "
b101 !
#6100000
0%
b100 #
#6150000
0&
1$
b1110 #
#6200000
0$
1&
#6250000
0&
#7000000
b11 "
b111 !
#7100000
b110 #
#7150000
b10 #
#7200000
1%
#7250000
b1010 #
1&
#8000000
b1011 "
b1011 !
#8100000
b1110 #
1$
#8150000
0%
0&
#8200000
b110 #
1&
#9000000
b1000 "
b1000 !
#9150000
b0 #
#10000000
b111 !
#10100000
b1111 #
0$
#10150000
0&
#11000000
b111 "
#11100000
1%
b0 #
#11150000
b1110 #
1&
#12000000
b10 "
b101 !
#12100000
0%
b1001 #
#12150000
1%
0&
b111 #
#12200000
1&
b1011 #
0%
#12250000
1%
b111 #
0&
#12300000
0%
b1111 #
1&
#12350000
b111 #
0&
#13000000
b11 "
#13100000
b110 #
#13150000
b100 #
#13250000
b0 #
#13300000
1%
#13350000
b1000 #
1&
#14000000
b1101 "
b1011 !
#14100000
1$
#14150000
0&
#15000000
b1100 "
#15100000
b1001 #
#15150000
b1011 #
#15250000
b1111 #
#15300000
0%
#15350000
b111 #
1&
