adder.v
`define AND and #50
`define OR or #50
`define XOR xor #50
`define NOT not #50

// Adder circuit

/*module behavioralFullAdder
(
    output sum,
    output carryout,
    input a,
    input b,
    input carryin
);
    // Uses concatenation operator and built-in '+'
    assign {carryout, sum}=a+b+carryin;
endmodule*/

module structFullAdder
(
    output sum,
    output carryout,
    input a,
    input b,
    input carryin
);
  wire AxorB;
	wire AandB;
	wire AxorBandCarryIn;

	`XOR (AxorB, a, b);
	`XOR (sum, AxorB, carryin);
	`AND (AandB, a, b);
	`AND (AxorBandCarryIn, AxorB, carryin);
	`OR (carryout, AxorBandCarryIn, AandB);
endmodule

module FullAdder4bit
(
  output[3:0] sum,  // 2's complement sum of a and b
  output carryout,  // Carry out of the summation of a and b
  output overflow,  // True if the calculation resulted in an overflow
  input[3:0] a,     // First operand in 2's complement format
  input[3:0] b      // Second operand in 2's complement format
);

	wire carryout0;
	wire carryout1;
	wire carryout2;

	structFullAdder a0(sum[0], carryout0, a[0], b[0], 1'b0);
	structFullAdder a1(sum[1], carryout1, a[1], b[1], carryout0);
	structFullAdder a2(sum[2], carryout2, a[2], b[2], carryout1);
	structFullAdder a3(sum[3], carryout, a[3], b[3], carryout2);

  `XOR (overflow, carryout2, carryout);
endmodule

adder.t.v
`timescale 1 ns / 1 ps
`include "adder.v"

module test4BitFullAdder();
  reg[3:0] a;
	reg[3:0] b;
	wire[3:0] sum;
  wire carryout;
	wire overflow;
  integer i;
  integer j;

	FullAdder4bit adder(sum, carryout, overflow, a, b);

  initial begin
  	$dumpfile("fulladder.vcd");
  	$dumpvars(0, a[3:0], b[3:0], sum[3:0], carryout, overflow);

    $display(" a  |  b  |  S  S3 |  COut  |  OverFlow");
    //for(i = -8; i < 8; i = i + 7)
    //begin
      //for(j = -8; j < 8; j = j + 1)
      //begin

    a = -8;
    b = -8;
    #1000
    $display(" %d |  %d | %d   %b |    %b   |        %b ", $signed(a), $signed(b), $signed(sum), sum[3], carryout, overflow);
    a = 7;
    b = -8;
    #1000
    $display(" %d |  %d | %d   %b |    %b   |        %b ", $signed(a), $signed(b), $signed(sum), sum[3], carryout, overflow);
    a = 7;
    b = 7;
    #1000
    $display(" %d |  %d | %d   %b |    %b   |        %b ", $signed(a), $signed(b), $signed(sum), sum[3], carryout, overflow);
    a = 5;
    b = 2;
    #1000
    $display(" %d |  %d | %d   %b |    %b   |        %b ", $signed(a), $signed(b), $signed(sum), sum[3], carryout, overflow);
    a = 5;
    b = 3;
    #1000
    $display(" %d |  %d | %d   %b |    %b   |        %b ", $signed(a), $signed(b), $signed(sum), sum[3], carryout, overflow);
    a = -5;
    b = -3;
    #1000
    $display(" %d |  %d | %d   %b |    %b   |        %b ", $signed(a), $signed(b), $signed(sum), sum[3], carryout, overflow);
    a = -5;
    b = -4;
    #1000
    $display(" %d |  %d | %d   %b |    %b   |        %b ", $signed(a), $signed(b), $signed(sum), sum[3], carryout, overflow);

      //end
    //end

    end
endmodule

fulladder.vcd
$date
	Tue Sep 26 14:25:51 2017
$end
$version
	Icarus Verilog
$end
$timescale
	1ps
$end
$scope module test4BitFullAdder $end
$var reg 4 ! a [3:0] $end
$upscope $end
$scope module test4BitFullAdder $end
$var reg 4 " b [3:0] $end
$upscope $end
$scope module test4BitFullAdder $end
$var wire 4 # sum [3:0] $end
$upscope $end
$scope module test4BitFullAdder $end
$var wire 1 $ carryout $end
$upscope $end
$scope module test4BitFullAdder $end
$var wire 1 % overflow $end
$upscope $end
$enddefinitions $end
#0
$dumpvars
x%
x$
bx #
b1000 "
b1000 !
$end
#100000
bx0 #
1$
#150000
bx00 #
#200000
b0 #
1%
#1000000
b111 !
#1100000
b1111 #
0$
#1150000
0%
#2000000
b111 "
#2100000
b0 #
#2150000
b1110 #
1%
#3000000
b10 "
b101 !
#3100000
b1001 #
#3150000
0%
b111 #
#3200000
1%
b1011 #
#3250000
b111 #
0%
#3300000
b1111 #
1%
#3350000
b111 #
0%
#4000000
b11 "
#4100000
b110 #
#4150000
b100 #
#4250000
b0 #
#4350000
b1000 #
1%
#5000000
b1101 "
b1011 !
#5100000
1$
#5150000
0%
#6000000
b1100 "
#6100000
b1001 #
#6150000
b1011 #
#6250000
b1111 #
#6350000
b111 #
1%
